toppra/interpolator.py
toppra/__init__.py
toppra/_CythonUtils.cpython-36m-x86_64-linux-gnu.so
toppra/utils.py
toppra/simplepath.py
toppra/constants.py
toppra/exceptions.py
toppra/parametrizer.py
toppra/planning_utils.py
toppra/constraint/constraint.py
toppra/constraint/joint_torque.py
toppra/constraint/__init__.py
toppra/constraint/linear_constraint.py
toppra/constraint/linear_second_order.py
toppra/constraint/linear_joint_acceleration.py
toppra/constraint/conic_constraint.py
toppra/constraint/linear_joint_velocity.py
toppra/cpp/__init__.py
toppra/algorithm/algorithm.py
toppra/algorithm/__init__.py
toppra/algorithm/reachabilitybased/reachability_algorithm.py
toppra/algorithm/reachabilitybased/__init__.py
toppra/algorithm/reachabilitybased/desired_duration_algorithm.py
toppra/algorithm/reachabilitybased/time_optimal_algorithm.py
toppra/solverwrapper/ecos_solverwrapper.py
toppra/solverwrapper/solverwrapper.py
toppra/solverwrapper/__init__.py
toppra/solverwrapper/qpoases_solverwrapper.py
toppra/solverwrapper/hot_qpoases_solverwrapper.py
toppra/solverwrapper/cy_seidel_solverwrapper.cpython-36m-x86_64-linux-gnu.so
toppra/solverwrapper/cvxpy_solverwrapper.py
toppra-0.6.0.dist-info/top_level.txt
toppra-0.6.0.dist-info/LICENSE
toppra-0.6.0.dist-info/RECORD
toppra-0.6.0.dist-info/WHEEL
toppra-0.6.0.dist-info/METADATA
