Metadata-Version: 2.1
Name: toppra
Version: 0.6.0
Summary: toppra: time-optimal parametrization of trajectories for robots subject to constraints.
Home-page: https://github.com/hungpham2511/toppra
Author: Hung Pham
Author-email: hungpham2511@gmail.com
License: MIT
Platform: UNKNOWN
License-File: LICENSE
Requires-Dist: scipy (>0.18)
Requires-Dist: numpy
Requires-Dist: matplotlib
Provides-Extra: dev
Requires-Dist: PyYAML (<=5.3.1) ; extra == 'dev'
Requires-Dist: msgpack (<=1.0.1) ; extra == 'dev'
Requires-Dist: numpy ; extra == 'dev'
Requires-Dist: cython ; extra == 'dev'
Requires-Dist: invoke ; extra == 'dev'
Requires-Dist: strip-hints ; extra == 'dev'
Requires-Dist: ipython ; extra == 'dev'
Requires-Dist: ipdb ; extra == 'dev'
Requires-Dist: cvxopt ; extra == 'dev'
Requires-Dist: cvxpy ; extra == 'dev'
Requires-Dist: pandas ; extra == 'dev'
Requires-Dist: tabulate ; extra == 'dev'
Requires-Dist: pytest ; extra == 'dev'
Requires-Dist: pylint ; extra == 'dev'
Requires-Dist: mypy ; extra == 'dev'
